{
  "metadata": {
    "timestamp": "2026-04-19T00-44-28-198Z",
    "environment": "FlappyBird",
    "maxStepsPerEpisode": 5000,
    "evalSeed": 424242,
    "pipeGap": 150,
    "rewards": {
      "survive": 0.1,
      "passPipe": 1,
      "collision": -1,
      "proximityScale": 0.5
    }
  },
  "qlearning": {
    "trainingEpisodes": 20000,
    "trainingTimeSec": 3.16,
    "hyperparameters": {
      "alpha": 0.1,
      "gamma": 0.95,
      "epsilonStart": 1,
      "epsilonEnd": 0.01,
      "epsilonDecay": 0.9997122182804811,
      "bins": {
        "dx": {
          "min": -50,
          "max": 300,
          "count": 15
        },
        "dy": {
          "min": -200,
          "max": 200,
          "count": 20
        },
        "vy": {
          "min": -8,
          "max": 8,
          "count": 15
        }
      },
      "qTableSize": 615
    },
    "learningCurve": [
      {
        "episode": 200,
        "avgScore": 0.05,
        "maxScore": 1,
        "epsilon": 0.9441,
        "qTableSize": 367
      },
      {
        "episode": 400,
        "avgScore": 0.05,
        "maxScore": 1,
        "epsilon": 0.8913,
        "qTableSize": 446
      },
      {
        "episode": 600,
        "avgScore": 0.1,
        "maxScore": 2,
        "epsilon": 0.8414,
        "qTableSize": 510
      },
      {
        "episode": 800,
        "avgScore": 0.04,
        "maxScore": 1,
        "epsilon": 0.7943,
        "qTableSize": 544
      },
      {
        "episode": 1000,
        "avgScore": 0.07,
        "maxScore": 2,
        "epsilon": 0.7499,
        "qTableSize": 561
      },
      {
        "episode": 1200,
        "avgScore": 0.12,
        "maxScore": 1,
        "epsilon": 0.7079,
        "qTableSize": 580
      },
      {
        "episode": 1400,
        "avgScore": 0.13,
        "maxScore": 4,
        "epsilon": 0.6683,
        "qTableSize": 587
      },
      {
        "episode": 1600,
        "avgScore": 0.11,
        "maxScore": 2,
        "epsilon": 0.631,
        "qTableSize": 593
      },
      {
        "episode": 1800,
        "avgScore": 0.18,
        "maxScore": 2,
        "epsilon": 0.5957,
        "qTableSize": 596
      },
      {
        "episode": 2000,
        "avgScore": 0.18,
        "maxScore": 3,
        "epsilon": 0.5623,
        "qTableSize": 602
      },
      {
        "episode": 2200,
        "avgScore": 0.23,
        "maxScore": 3,
        "epsilon": 0.5309,
        "qTableSize": 608
      },
      {
        "episode": 2400,
        "avgScore": 0.34,
        "maxScore": 5,
        "epsilon": 0.5012,
        "qTableSize": 608
      },
      {
        "episode": 2600,
        "avgScore": 0.35,
        "maxScore": 3,
        "epsilon": 0.4732,
        "qTableSize": 611
      },
      {
        "episode": 2800,
        "avgScore": 0.45,
        "maxScore": 4,
        "epsilon": 0.4467,
        "qTableSize": 611
      },
      {
        "episode": 3000,
        "avgScore": 0.36,
        "maxScore": 3,
        "epsilon": 0.4217,
        "qTableSize": 612
      },
      {
        "episode": 3200,
        "avgScore": 0.51,
        "maxScore": 4,
        "epsilon": 0.3981,
        "qTableSize": 612
      },
      {
        "episode": 3400,
        "avgScore": 0.54,
        "maxScore": 8,
        "epsilon": 0.3758,
        "qTableSize": 612
      },
      {
        "episode": 3600,
        "avgScore": 0.51,
        "maxScore": 7,
        "epsilon": 0.3548,
        "qTableSize": 613
      },
      {
        "episode": 3800,
        "avgScore": 0.53,
        "maxScore": 4,
        "epsilon": 0.335,
        "qTableSize": 613
      },
      {
        "episode": 4000,
        "avgScore": 0.6,
        "maxScore": 4,
        "epsilon": 0.3162,
        "qTableSize": 613
      },
      {
        "episode": 4200,
        "avgScore": 0.66,
        "maxScore": 6,
        "epsilon": 0.2985,
        "qTableSize": 613
      },
      {
        "episode": 4400,
        "avgScore": 0.76,
        "maxScore": 5,
        "epsilon": 0.2818,
        "qTableSize": 613
      },
      {
        "episode": 4600,
        "avgScore": 0.81,
        "maxScore": 6,
        "epsilon": 0.2661,
        "qTableSize": 613
      },
      {
        "episode": 4800,
        "avgScore": 0.95,
        "maxScore": 9,
        "epsilon": 0.2512,
        "qTableSize": 613
      },
      {
        "episode": 5000,
        "avgScore": 1.01,
        "maxScore": 8,
        "epsilon": 0.2371,
        "qTableSize": 613
      },
      {
        "episode": 5200,
        "avgScore": 1.13,
        "maxScore": 8,
        "epsilon": 0.2239,
        "qTableSize": 613
      },
      {
        "episode": 5400,
        "avgScore": 1.39,
        "maxScore": 12,
        "epsilon": 0.2113,
        "qTableSize": 613
      },
      {
        "episode": 5600,
        "avgScore": 1.19,
        "maxScore": 7,
        "epsilon": 0.1995,
        "qTableSize": 613
      },
      {
        "episode": 5800,
        "avgScore": 0.95,
        "maxScore": 11,
        "epsilon": 0.1884,
        "qTableSize": 613
      },
      {
        "episode": 6000,
        "avgScore": 1.24,
        "maxScore": 9,
        "epsilon": 0.1778,
        "qTableSize": 613
      },
      {
        "episode": 6200,
        "avgScore": 1.43,
        "maxScore": 10,
        "epsilon": 0.1679,
        "qTableSize": 613
      },
      {
        "episode": 6400,
        "avgScore": 1.58,
        "maxScore": 15,
        "epsilon": 0.1585,
        "qTableSize": 613
      },
      {
        "episode": 6600,
        "avgScore": 1.29,
        "maxScore": 7,
        "epsilon": 0.1496,
        "qTableSize": 613
      },
      {
        "episode": 6800,
        "avgScore": 1.7,
        "maxScore": 13,
        "epsilon": 0.1413,
        "qTableSize": 613
      },
      {
        "episode": 7000,
        "avgScore": 1.89,
        "maxScore": 12,
        "epsilon": 0.1334,
        "qTableSize": 613
      },
      {
        "episode": 7200,
        "avgScore": 2.17,
        "maxScore": 23,
        "epsilon": 0.1259,
        "qTableSize": 613
      },
      {
        "episode": 7400,
        "avgScore": 1.88,
        "maxScore": 12,
        "epsilon": 0.1189,
        "qTableSize": 613
      },
      {
        "episode": 7600,
        "avgScore": 1.43,
        "maxScore": 12,
        "epsilon": 0.1122,
        "qTableSize": 613
      },
      {
        "episode": 7800,
        "avgScore": 2.56,
        "maxScore": 13,
        "epsilon": 0.1059,
        "qTableSize": 613
      },
      {
        "episode": 8000,
        "avgScore": 2.5,
        "maxScore": 21,
        "epsilon": 0.1,
        "qTableSize": 613
      },
      {
        "episode": 8200,
        "avgScore": 1.48,
        "maxScore": 7,
        "epsilon": 0.0944,
        "qTableSize": 613
      },
      {
        "episode": 8400,
        "avgScore": 2.12,
        "maxScore": 14,
        "epsilon": 0.0891,
        "qTableSize": 613
      },
      {
        "episode": 8600,
        "avgScore": 2.33,
        "maxScore": 10,
        "epsilon": 0.0841,
        "qTableSize": 613
      },
      {
        "episode": 8800,
        "avgScore": 1.64,
        "maxScore": 13,
        "epsilon": 0.0794,
        "qTableSize": 613
      },
      {
        "episode": 9000,
        "avgScore": 1.59,
        "maxScore": 9,
        "epsilon": 0.075,
        "qTableSize": 613
      },
      {
        "episode": 9200,
        "avgScore": 2.99,
        "maxScore": 13,
        "epsilon": 0.0708,
        "qTableSize": 614
      },
      {
        "episode": 9400,
        "avgScore": 2.48,
        "maxScore": 10,
        "epsilon": 0.0668,
        "qTableSize": 614
      },
      {
        "episode": 9600,
        "avgScore": 2.8,
        "maxScore": 16,
        "epsilon": 0.0631,
        "qTableSize": 614
      },
      {
        "episode": 9800,
        "avgScore": 3.9,
        "maxScore": 25,
        "epsilon": 0.0596,
        "qTableSize": 614
      },
      {
        "episode": 10000,
        "avgScore": 2.62,
        "maxScore": 15,
        "epsilon": 0.0562,
        "qTableSize": 614
      },
      {
        "episode": 10200,
        "avgScore": 3,
        "maxScore": 16,
        "epsilon": 0.0531,
        "qTableSize": 614
      },
      {
        "episode": 10400,
        "avgScore": 3.27,
        "maxScore": 18,
        "epsilon": 0.0501,
        "qTableSize": 614
      },
      {
        "episode": 10600,
        "avgScore": 3.46,
        "maxScore": 28,
        "epsilon": 0.0473,
        "qTableSize": 614
      },
      {
        "episode": 10800,
        "avgScore": 3.81,
        "maxScore": 25,
        "epsilon": 0.0447,
        "qTableSize": 614
      },
      {
        "episode": 11000,
        "avgScore": 2.2,
        "maxScore": 13,
        "epsilon": 0.0422,
        "qTableSize": 614
      },
      {
        "episode": 11200,
        "avgScore": 4.05,
        "maxScore": 37,
        "epsilon": 0.0398,
        "qTableSize": 614
      },
      {
        "episode": 11400,
        "avgScore": 3.6,
        "maxScore": 20,
        "epsilon": 0.0376,
        "qTableSize": 614
      },
      {
        "episode": 11600,
        "avgScore": 1.31,
        "maxScore": 10,
        "epsilon": 0.0355,
        "qTableSize": 614
      },
      {
        "episode": 11800,
        "avgScore": 0.61,
        "maxScore": 4,
        "epsilon": 0.0335,
        "qTableSize": 614
      },
      {
        "episode": 12000,
        "avgScore": 0.88,
        "maxScore": 6,
        "epsilon": 0.0316,
        "qTableSize": 614
      },
      {
        "episode": 12200,
        "avgScore": 1.58,
        "maxScore": 8,
        "epsilon": 0.0299,
        "qTableSize": 614
      },
      {
        "episode": 12400,
        "avgScore": 2.04,
        "maxScore": 9,
        "epsilon": 0.0282,
        "qTableSize": 614
      },
      {
        "episode": 12600,
        "avgScore": 3.27,
        "maxScore": 20,
        "epsilon": 0.0266,
        "qTableSize": 614
      },
      {
        "episode": 12800,
        "avgScore": 4.27,
        "maxScore": 28,
        "epsilon": 0.0251,
        "qTableSize": 614
      },
      {
        "episode": 13000,
        "avgScore": 3.67,
        "maxScore": 21,
        "epsilon": 0.0237,
        "qTableSize": 614
      },
      {
        "episode": 13200,
        "avgScore": 2.27,
        "maxScore": 18,
        "epsilon": 0.0224,
        "qTableSize": 614
      },
      {
        "episode": 13400,
        "avgScore": 1.65,
        "maxScore": 8,
        "epsilon": 0.0211,
        "qTableSize": 614
      },
      {
        "episode": 13600,
        "avgScore": 1.99,
        "maxScore": 16,
        "epsilon": 0.02,
        "qTableSize": 614
      },
      {
        "episode": 13800,
        "avgScore": 1.55,
        "maxScore": 6,
        "epsilon": 0.0188,
        "qTableSize": 614
      },
      {
        "episode": 14000,
        "avgScore": 3.02,
        "maxScore": 18,
        "epsilon": 0.0178,
        "qTableSize": 614
      },
      {
        "episode": 14200,
        "avgScore": 2.57,
        "maxScore": 25,
        "epsilon": 0.0168,
        "qTableSize": 614
      },
      {
        "episode": 14400,
        "avgScore": 1.43,
        "maxScore": 8,
        "epsilon": 0.0158,
        "qTableSize": 614
      },
      {
        "episode": 14600,
        "avgScore": 4.83,
        "maxScore": 33,
        "epsilon": 0.015,
        "qTableSize": 614
      },
      {
        "episode": 14800,
        "avgScore": 6.96,
        "maxScore": 26,
        "epsilon": 0.0141,
        "qTableSize": 614
      },
      {
        "episode": 15000,
        "avgScore": 4.74,
        "maxScore": 32,
        "epsilon": 0.0133,
        "qTableSize": 614
      },
      {
        "episode": 15200,
        "avgScore": 3.85,
        "maxScore": 20,
        "epsilon": 0.0126,
        "qTableSize": 614
      },
      {
        "episode": 15400,
        "avgScore": 4.33,
        "maxScore": 21,
        "epsilon": 0.0119,
        "qTableSize": 614
      },
      {
        "episode": 15600,
        "avgScore": 6.62,
        "maxScore": 41,
        "epsilon": 0.0112,
        "qTableSize": 614
      },
      {
        "episode": 15800,
        "avgScore": 7.49,
        "maxScore": 48,
        "epsilon": 0.0106,
        "qTableSize": 614
      },
      {
        "episode": 16000,
        "avgScore": 2.59,
        "maxScore": 16,
        "epsilon": 0.01,
        "qTableSize": 614
      },
      {
        "episode": 16200,
        "avgScore": 4.55,
        "maxScore": 26,
        "epsilon": 0.01,
        "qTableSize": 614
      },
      {
        "episode": 16400,
        "avgScore": 4.88,
        "maxScore": 29,
        "epsilon": 0.01,
        "qTableSize": 614
      },
      {
        "episode": 16600,
        "avgScore": 2.56,
        "maxScore": 10,
        "epsilon": 0.01,
        "qTableSize": 615
      },
      {
        "episode": 16800,
        "avgScore": 1.93,
        "maxScore": 7,
        "epsilon": 0.01,
        "qTableSize": 615
      },
      {
        "episode": 17000,
        "avgScore": 2.85,
        "maxScore": 14,
        "epsilon": 0.01,
        "qTableSize": 615
      },
      {
        "episode": 17200,
        "avgScore": 2.73,
        "maxScore": 13,
        "epsilon": 0.01,
        "qTableSize": 615
      },
      {
        "episode": 17400,
        "avgScore": 2.83,
        "maxScore": 11,
        "epsilon": 0.01,
        "qTableSize": 615
      },
      {
        "episode": 17600,
        "avgScore": 6.08,
        "maxScore": 40,
        "epsilon": 0.01,
        "qTableSize": 615
      },
      {
        "episode": 17800,
        "avgScore": 5.09,
        "maxScore": 48,
        "epsilon": 0.01,
        "qTableSize": 615
      },
      {
        "episode": 18000,
        "avgScore": 4.99,
        "maxScore": 26,
        "epsilon": 0.01,
        "qTableSize": 615
      },
      {
        "episode": 18200,
        "avgScore": 5.38,
        "maxScore": 38,
        "epsilon": 0.01,
        "qTableSize": 615
      },
      {
        "episode": 18400,
        "avgScore": 3.21,
        "maxScore": 26,
        "epsilon": 0.01,
        "qTableSize": 615
      },
      {
        "episode": 18600,
        "avgScore": 6.12,
        "maxScore": 43,
        "epsilon": 0.01,
        "qTableSize": 615
      },
      {
        "episode": 18800,
        "avgScore": 6.42,
        "maxScore": 38,
        "epsilon": 0.01,
        "qTableSize": 615
      },
      {
        "episode": 19000,
        "avgScore": 6.21,
        "maxScore": 26,
        "epsilon": 0.01,
        "qTableSize": 615
      },
      {
        "episode": 19200,
        "avgScore": 5.09,
        "maxScore": 34,
        "epsilon": 0.01,
        "qTableSize": 615
      },
      {
        "episode": 19400,
        "avgScore": 2.64,
        "maxScore": 24,
        "epsilon": 0.01,
        "qTableSize": 615
      },
      {
        "episode": 19600,
        "avgScore": 3.33,
        "maxScore": 25,
        "epsilon": 0.01,
        "qTableSize": 615
      },
      {
        "episode": 19800,
        "avgScore": 3.76,
        "maxScore": 15,
        "epsilon": 0.01,
        "qTableSize": 615
      },
      {
        "episode": 20000,
        "avgScore": 3.86,
        "maxScore": 42,
        "epsilon": 0.01,
        "qTableSize": 615
      }
    ],
    "checkpoints": [
      {
        "episode": 2000,
        "mean": 1.52,
        "max": 7,
        "min": 0,
        "stdDev": 1.64,
        "median": 1
      },
      {
        "episode": 4000,
        "mean": 4.06,
        "max": 19,
        "min": 0,
        "stdDev": 3.82,
        "median": 3
      },
      {
        "episode": 6000,
        "mean": 3.83,
        "max": 18,
        "min": 1,
        "stdDev": 3.69,
        "median": 2.5
      },
      {
        "episode": 8000,
        "mean": 2.89,
        "max": 10,
        "min": 1,
        "stdDev": 2.09,
        "median": 2
      },
      {
        "episode": 10000,
        "mean": 5.03,
        "max": 30,
        "min": 1,
        "stdDev": 4.4,
        "median": 4
      },
      {
        "episode": 12000,
        "mean": 1.37,
        "max": 7,
        "min": 0,
        "stdDev": 1.46,
        "median": 1
      },
      {
        "episode": 14000,
        "mean": 4.68,
        "max": 28,
        "min": 1,
        "stdDev": 4.31,
        "median": 3.5
      },
      {
        "episode": 16000,
        "mean": 4,
        "max": 15,
        "min": 1,
        "stdDev": 3.25,
        "median": 3
      },
      {
        "episode": 18000,
        "mean": 10.03,
        "max": 40,
        "min": 2,
        "stdDev": 7.51,
        "median": 7.5
      },
      {
        "episode": 20000,
        "mean": 5.53,
        "max": 35,
        "min": 1,
        "stdDev": 5.17,
        "median": 5
      }
    ],
    "finalEval": {
      "mean": 5.47,
      "max": 43,
      "min": 0,
      "stdDev": 5.85,
      "median": 4,
      "episodes": 200,
      "rawScores": [
        10,
        1,
        10,
        2,
        1,
        7,
        10,
        6,
        6,
        1,
        9,
        3,
        1,
        1,
        1,
        2,
        7,
        6,
        10,
        13,
        3,
        14,
        8,
        1,
        13,
        1,
        6,
        3,
        4,
        2,
        5,
        2,
        5,
        3,
        5,
        1,
        1,
        1,
        1,
        1,
        4,
        8,
        1,
        1,
        1,
        12,
        5,
        2,
        1,
        8,
        2,
        35,
        1,
        3,
        6,
        5,
        10,
        3,
        7,
        8,
        5,
        4,
        1,
        6,
        5,
        4,
        5,
        5,
        7,
        4,
        5,
        5,
        3,
        5,
        20,
        7,
        1,
        17,
        4,
        12,
        24,
        4,
        2,
        8,
        7,
        1,
        1,
        3,
        9,
        8,
        5,
        3,
        8,
        2,
        4,
        5,
        9,
        5,
        1,
        9,
        4,
        1,
        1,
        11,
        11,
        2,
        16,
        6,
        2,
        2,
        2,
        1,
        2,
        3,
        6,
        3,
        1,
        1,
        1,
        8,
        7,
        19,
        3,
        5,
        5,
        1,
        1,
        12,
        3,
        1,
        2,
        1,
        23,
        7,
        9,
        1,
        4,
        2,
        1,
        4,
        3,
        4,
        7,
        11,
        1,
        1,
        22,
        1,
        1,
        43,
        18,
        7,
        3,
        2,
        1,
        2,
        3,
        4,
        2,
        1,
        4,
        2,
        2,
        7,
        1,
        1,
        4,
        14,
        13,
        3,
        2,
        1,
        2,
        5,
        1,
        0,
        9,
        15,
        11,
        5,
        2,
        17,
        7,
        1,
        2,
        1,
        4,
        2,
        1,
        7,
        2,
        14,
        2,
        1,
        7,
        1,
        15,
        16,
        2,
        3
      ]
    }
  },
  "dqn": {
    "trainingEpisodes": 5000,
    "trainingTimeSec": 269.53,
    "hyperparameters": {
      "gamma": 0.99,
      "learningRate": 0.001,
      "epsilonStart": 1,
      "epsilonEnd": 0.01,
      "epsilonDecay": 0.9988493699365052,
      "batchSize": 64,
      "replayBufferSize": 10000,
      "targetUpdateFreq": 5000,
      "networkArchitecture": "3 → 24(ReLU) → 24(ReLU) → 2(Linear)",
      "algorithm": "Vanilla DQN: target = r + γ·max Q_target(s',a')"
    },
    "learningCurve": [
      {
        "episode": 50,
        "avgScore": 0,
        "maxScore": 0,
        "epsilon": 0.9441
      },
      {
        "episode": 100,
        "avgScore": 0.04,
        "maxScore": 1,
        "epsilon": 0.8913
      },
      {
        "episode": 150,
        "avgScore": 0.08,
        "maxScore": 2,
        "epsilon": 0.8414
      },
      {
        "episode": 200,
        "avgScore": 0.04,
        "maxScore": 1,
        "epsilon": 0.7943
      },
      {
        "episode": 250,
        "avgScore": 0.18,
        "maxScore": 1,
        "epsilon": 0.7499
      },
      {
        "episode": 300,
        "avgScore": 0.1,
        "maxScore": 1,
        "epsilon": 0.7079
      },
      {
        "episode": 350,
        "avgScore": 0.22,
        "maxScore": 2,
        "epsilon": 0.6683
      },
      {
        "episode": 400,
        "avgScore": 0.32,
        "maxScore": 2,
        "epsilon": 0.631
      },
      {
        "episode": 450,
        "avgScore": 0.26,
        "maxScore": 1,
        "epsilon": 0.5957
      },
      {
        "episode": 500,
        "avgScore": 0.26,
        "maxScore": 2,
        "epsilon": 0.5623
      },
      {
        "episode": 550,
        "avgScore": 0.32,
        "maxScore": 3,
        "epsilon": 0.5309
      },
      {
        "episode": 600,
        "avgScore": 0.58,
        "maxScore": 5,
        "epsilon": 0.5012
      },
      {
        "episode": 650,
        "avgScore": 0.58,
        "maxScore": 4,
        "epsilon": 0.4732
      },
      {
        "episode": 700,
        "avgScore": 0.4,
        "maxScore": 4,
        "epsilon": 0.4467
      },
      {
        "episode": 750,
        "avgScore": 0.68,
        "maxScore": 6,
        "epsilon": 0.4217
      },
      {
        "episode": 800,
        "avgScore": 0.6,
        "maxScore": 3,
        "epsilon": 0.3981
      },
      {
        "episode": 850,
        "avgScore": 0.7,
        "maxScore": 4,
        "epsilon": 0.3758
      },
      {
        "episode": 900,
        "avgScore": 1.1,
        "maxScore": 6,
        "epsilon": 0.3548
      },
      {
        "episode": 950,
        "avgScore": 1.16,
        "maxScore": 6,
        "epsilon": 0.335
      },
      {
        "episode": 1000,
        "avgScore": 0.8,
        "maxScore": 4,
        "epsilon": 0.3162
      },
      {
        "episode": 1050,
        "avgScore": 1.06,
        "maxScore": 7,
        "epsilon": 0.2985
      },
      {
        "episode": 1100,
        "avgScore": 1.18,
        "maxScore": 7,
        "epsilon": 0.2818
      },
      {
        "episode": 1150,
        "avgScore": 1.28,
        "maxScore": 6,
        "epsilon": 0.2661
      },
      {
        "episode": 1200,
        "avgScore": 1.14,
        "maxScore": 8,
        "epsilon": 0.2512
      },
      {
        "episode": 1250,
        "avgScore": 1.98,
        "maxScore": 12,
        "epsilon": 0.2371
      },
      {
        "episode": 1300,
        "avgScore": 0.98,
        "maxScore": 6,
        "epsilon": 0.2239
      },
      {
        "episode": 1350,
        "avgScore": 1.9,
        "maxScore": 8,
        "epsilon": 0.2113
      },
      {
        "episode": 1400,
        "avgScore": 2.16,
        "maxScore": 11,
        "epsilon": 0.1995
      },
      {
        "episode": 1450,
        "avgScore": 1.34,
        "maxScore": 5,
        "epsilon": 0.1884
      },
      {
        "episode": 1500,
        "avgScore": 2.28,
        "maxScore": 15,
        "epsilon": 0.1778
      },
      {
        "episode": 1550,
        "avgScore": 1.9,
        "maxScore": 9,
        "epsilon": 0.1679
      },
      {
        "episode": 1600,
        "avgScore": 2.28,
        "maxScore": 16,
        "epsilon": 0.1585
      },
      {
        "episode": 1650,
        "avgScore": 1.54,
        "maxScore": 7,
        "epsilon": 0.1496
      },
      {
        "episode": 1700,
        "avgScore": 1.92,
        "maxScore": 9,
        "epsilon": 0.1413
      },
      {
        "episode": 1750,
        "avgScore": 2.76,
        "maxScore": 13,
        "epsilon": 0.1334
      },
      {
        "episode": 1800,
        "avgScore": 2.54,
        "maxScore": 10,
        "epsilon": 0.1259
      },
      {
        "episode": 1850,
        "avgScore": 2.8,
        "maxScore": 13,
        "epsilon": 0.1189
      },
      {
        "episode": 1900,
        "avgScore": 1.88,
        "maxScore": 10,
        "epsilon": 0.1122
      },
      {
        "episode": 1950,
        "avgScore": 2.88,
        "maxScore": 15,
        "epsilon": 0.1059
      },
      {
        "episode": 2000,
        "avgScore": 3.4,
        "maxScore": 11,
        "epsilon": 0.1
      },
      {
        "episode": 2050,
        "avgScore": 2.9,
        "maxScore": 14,
        "epsilon": 0.0944
      },
      {
        "episode": 2100,
        "avgScore": 3.74,
        "maxScore": 21,
        "epsilon": 0.0891
      },
      {
        "episode": 2150,
        "avgScore": 4.1,
        "maxScore": 13,
        "epsilon": 0.0841
      },
      {
        "episode": 2200,
        "avgScore": 3.24,
        "maxScore": 21,
        "epsilon": 0.0794
      },
      {
        "episode": 2250,
        "avgScore": 2.92,
        "maxScore": 17,
        "epsilon": 0.075
      },
      {
        "episode": 2300,
        "avgScore": 3.08,
        "maxScore": 16,
        "epsilon": 0.0708
      },
      {
        "episode": 2350,
        "avgScore": 3.82,
        "maxScore": 19,
        "epsilon": 0.0668
      },
      {
        "episode": 2400,
        "avgScore": 4.02,
        "maxScore": 16,
        "epsilon": 0.0631
      },
      {
        "episode": 2450,
        "avgScore": 4.72,
        "maxScore": 22,
        "epsilon": 0.0596
      },
      {
        "episode": 2500,
        "avgScore": 4.38,
        "maxScore": 18,
        "epsilon": 0.0562
      },
      {
        "episode": 2550,
        "avgScore": 4.24,
        "maxScore": 19,
        "epsilon": 0.0531
      },
      {
        "episode": 2600,
        "avgScore": 4.7,
        "maxScore": 17,
        "epsilon": 0.0501
      },
      {
        "episode": 2650,
        "avgScore": 4.52,
        "maxScore": 20,
        "epsilon": 0.0473
      },
      {
        "episode": 2700,
        "avgScore": 4.9,
        "maxScore": 19,
        "epsilon": 0.0447
      },
      {
        "episode": 2750,
        "avgScore": 4.46,
        "maxScore": 15,
        "epsilon": 0.0422
      },
      {
        "episode": 2800,
        "avgScore": 3.5,
        "maxScore": 20,
        "epsilon": 0.0398
      },
      {
        "episode": 2850,
        "avgScore": 2.82,
        "maxScore": 21,
        "epsilon": 0.0376
      },
      {
        "episode": 2900,
        "avgScore": 3.68,
        "maxScore": 19,
        "epsilon": 0.0355
      },
      {
        "episode": 2950,
        "avgScore": 5.88,
        "maxScore": 21,
        "epsilon": 0.0335
      },
      {
        "episode": 3000,
        "avgScore": 3.88,
        "maxScore": 20,
        "epsilon": 0.0316
      },
      {
        "episode": 3050,
        "avgScore": 5.64,
        "maxScore": 21,
        "epsilon": 0.0299
      },
      {
        "episode": 3100,
        "avgScore": 5.24,
        "maxScore": 22,
        "epsilon": 0.0282
      },
      {
        "episode": 3150,
        "avgScore": 6.32,
        "maxScore": 20,
        "epsilon": 0.0266
      },
      {
        "episode": 3200,
        "avgScore": 6.54,
        "maxScore": 32,
        "epsilon": 0.0251
      },
      {
        "episode": 3250,
        "avgScore": 5.84,
        "maxScore": 35,
        "epsilon": 0.0237
      },
      {
        "episode": 3300,
        "avgScore": 5.28,
        "maxScore": 19,
        "epsilon": 0.0224
      },
      {
        "episode": 3350,
        "avgScore": 4.7,
        "maxScore": 20,
        "epsilon": 0.0211
      },
      {
        "episode": 3400,
        "avgScore": 6.36,
        "maxScore": 23,
        "epsilon": 0.02
      },
      {
        "episode": 3450,
        "avgScore": 5.58,
        "maxScore": 22,
        "epsilon": 0.0188
      },
      {
        "episode": 3500,
        "avgScore": 6.76,
        "maxScore": 31,
        "epsilon": 0.0178
      },
      {
        "episode": 3550,
        "avgScore": 5.32,
        "maxScore": 39,
        "epsilon": 0.0168
      },
      {
        "episode": 3600,
        "avgScore": 6.64,
        "maxScore": 40,
        "epsilon": 0.0158
      },
      {
        "episode": 3650,
        "avgScore": 7.72,
        "maxScore": 22,
        "epsilon": 0.015
      },
      {
        "episode": 3700,
        "avgScore": 7.08,
        "maxScore": 31,
        "epsilon": 0.0141
      },
      {
        "episode": 3750,
        "avgScore": 8.92,
        "maxScore": 35,
        "epsilon": 0.0133
      },
      {
        "episode": 3800,
        "avgScore": 6.64,
        "maxScore": 28,
        "epsilon": 0.0126
      },
      {
        "episode": 3850,
        "avgScore": 5.66,
        "maxScore": 22,
        "epsilon": 0.0119
      },
      {
        "episode": 3900,
        "avgScore": 4.08,
        "maxScore": 23,
        "epsilon": 0.0112
      },
      {
        "episode": 3950,
        "avgScore": 6.12,
        "maxScore": 28,
        "epsilon": 0.0106
      },
      {
        "episode": 4000,
        "avgScore": 9.34,
        "maxScore": 27,
        "epsilon": 0.01
      },
      {
        "episode": 4050,
        "avgScore": 10.34,
        "maxScore": 45,
        "epsilon": 0.01
      },
      {
        "episode": 4100,
        "avgScore": 8.16,
        "maxScore": 29,
        "epsilon": 0.01
      },
      {
        "episode": 4150,
        "avgScore": 7.68,
        "maxScore": 39,
        "epsilon": 0.01
      },
      {
        "episode": 4200,
        "avgScore": 8.04,
        "maxScore": 36,
        "epsilon": 0.01
      },
      {
        "episode": 4250,
        "avgScore": 9.1,
        "maxScore": 32,
        "epsilon": 0.01
      },
      {
        "episode": 4300,
        "avgScore": 8.3,
        "maxScore": 39,
        "epsilon": 0.01
      },
      {
        "episode": 4350,
        "avgScore": 8.16,
        "maxScore": 44,
        "epsilon": 0.01
      },
      {
        "episode": 4400,
        "avgScore": 8.2,
        "maxScore": 33,
        "epsilon": 0.01
      },
      {
        "episode": 4450,
        "avgScore": 6.7,
        "maxScore": 43,
        "epsilon": 0.01
      },
      {
        "episode": 4500,
        "avgScore": 8.16,
        "maxScore": 35,
        "epsilon": 0.01
      },
      {
        "episode": 4550,
        "avgScore": 7.12,
        "maxScore": 29,
        "epsilon": 0.01
      },
      {
        "episode": 4600,
        "avgScore": 8.62,
        "maxScore": 36,
        "epsilon": 0.01
      },
      {
        "episode": 4650,
        "avgScore": 4.52,
        "maxScore": 29,
        "epsilon": 0.01
      },
      {
        "episode": 4700,
        "avgScore": 4.48,
        "maxScore": 17,
        "epsilon": 0.01
      },
      {
        "episode": 4750,
        "avgScore": 7.02,
        "maxScore": 30,
        "epsilon": 0.01
      },
      {
        "episode": 4800,
        "avgScore": 6.9,
        "maxScore": 25,
        "epsilon": 0.01
      },
      {
        "episode": 4850,
        "avgScore": 11.16,
        "maxScore": 48,
        "epsilon": 0.01
      },
      {
        "episode": 4900,
        "avgScore": 7.56,
        "maxScore": 28,
        "epsilon": 0.01
      },
      {
        "episode": 4950,
        "avgScore": 6.82,
        "maxScore": 40,
        "epsilon": 0.01
      },
      {
        "episode": 5000,
        "avgScore": 4.54,
        "maxScore": 41,
        "epsilon": 0.01
      }
    ],
    "checkpoints": [
      {
        "episode": 500,
        "mean": 12.41,
        "max": 47,
        "min": 0,
        "stdDev": 9.7,
        "median": 10
      },
      {
        "episode": 1000,
        "mean": 7.48,
        "max": 36,
        "min": 0,
        "stdDev": 7.67,
        "median": 5
      },
      {
        "episode": 1500,
        "mean": 8.45,
        "max": 46,
        "min": 1,
        "stdDev": 8.39,
        "median": 5.5
      },
      {
        "episode": 2000,
        "mean": 9.87,
        "max": 48,
        "min": 0,
        "stdDev": 10.87,
        "median": 6.5
      },
      {
        "episode": 2500,
        "mean": 10.48,
        "max": 38,
        "min": 0,
        "stdDev": 9.42,
        "median": 8
      },
      {
        "episode": 3000,
        "mean": 10.89,
        "max": 48,
        "min": 0,
        "stdDev": 9.63,
        "median": 8
      },
      {
        "episode": 3500,
        "mean": 7.97,
        "max": 48,
        "min": 0,
        "stdDev": 8.94,
        "median": 5
      },
      {
        "episode": 4000,
        "mean": 11.36,
        "max": 48,
        "min": 1,
        "stdDev": 8.17,
        "median": 9
      },
      {
        "episode": 4500,
        "mean": 10.5,
        "max": 42,
        "min": 0,
        "stdDev": 9.31,
        "median": 7
      },
      {
        "episode": 5000,
        "mean": 6.77,
        "max": 40,
        "min": 0,
        "stdDev": 8.42,
        "median": 3
      }
    ],
    "finalEval": {
      "mean": 6.63,
      "max": 41,
      "min": 0,
      "stdDev": 7.88,
      "median": 4,
      "episodes": 200,
      "rawScores": [
        0,
        1,
        17,
        2,
        1,
        32,
        20,
        9,
        6,
        1,
        5,
        7,
        1,
        1,
        1,
        5,
        19,
        18,
        4,
        2,
        14,
        33,
        2,
        1,
        15,
        1,
        6,
        3,
        4,
        0,
        11,
        0,
        0,
        23,
        0,
        1,
        1,
        1,
        1,
        1,
        0,
        8,
        1,
        1,
        1,
        10,
        5,
        0,
        7,
        0,
        0,
        24,
        1,
        7,
        16,
        20,
        17,
        13,
        0,
        8,
        3,
        18,
        1,
        6,
        0,
        9,
        5,
        16,
        0,
        4,
        16,
        0,
        7,
        5,
        9,
        3,
        1,
        13,
        14,
        3,
        13,
        0,
        2,
        0,
        19,
        1,
        1,
        3,
        10,
        34,
        0,
        5,
        8,
        2,
        23,
        5,
        3,
        0,
        1,
        14,
        4,
        12,
        1,
        21,
        11,
        11,
        3,
        0,
        3,
        5,
        5,
        1,
        23,
        5,
        7,
        24,
        7,
        1,
        1,
        0,
        1,
        4,
        16,
        8,
        10,
        1,
        1,
        0,
        6,
        1,
        2,
        1,
        16,
        5,
        0,
        1,
        14,
        2,
        1,
        18,
        0,
        37,
        7,
        0,
        8,
        1,
        4,
        1,
        5,
        8,
        0,
        9,
        3,
        10,
        1,
        0,
        0,
        0,
        0,
        1,
        0,
        10,
        0,
        0,
        1,
        1,
        9,
        8,
        19,
        7,
        4,
        1,
        14,
        11,
        1,
        0,
        13,
        0,
        13,
        4,
        11,
        1,
        14,
        5,
        22,
        1,
        9,
        19,
        1,
        41,
        8,
        6,
        0,
        1,
        10,
        1,
        18,
        8,
        0,
        0
      ]
    }
  },
  "doubleDqn": {
    "trainingEpisodes": 5000,
    "trainingTimeSec": 294.83,
    "hyperparameters": {
      "gamma": 0.99,
      "learningRate": 0.001,
      "epsilonStart": 1,
      "epsilonEnd": 0.01,
      "epsilonDecay": 0.9988493699365052,
      "batchSize": 64,
      "replayBufferSize": 10000,
      "targetUpdateFreq": 5000,
      "networkArchitecture": "3 → 24(ReLU) → 24(ReLU) → 2(Linear)",
      "algorithm": "Double DQN: target = r + γ·Q_target(s', argmax Q_main(s',a'))"
    },
    "learningCurve": [
      {
        "episode": 50,
        "avgScore": 0.1,
        "maxScore": 2,
        "epsilon": 0.9441
      },
      {
        "episode": 100,
        "avgScore": 0,
        "maxScore": 0,
        "epsilon": 0.8913
      },
      {
        "episode": 150,
        "avgScore": 0.04,
        "maxScore": 2,
        "epsilon": 0.8414
      },
      {
        "episode": 200,
        "avgScore": 0.26,
        "maxScore": 2,
        "epsilon": 0.7943
      },
      {
        "episode": 250,
        "avgScore": 0.2,
        "maxScore": 2,
        "epsilon": 0.7499
      },
      {
        "episode": 300,
        "avgScore": 0.16,
        "maxScore": 1,
        "epsilon": 0.7079
      },
      {
        "episode": 350,
        "avgScore": 0.22,
        "maxScore": 2,
        "epsilon": 0.6683
      },
      {
        "episode": 400,
        "avgScore": 0.2,
        "maxScore": 1,
        "epsilon": 0.631
      },
      {
        "episode": 450,
        "avgScore": 0.26,
        "maxScore": 2,
        "epsilon": 0.5957
      },
      {
        "episode": 500,
        "avgScore": 0.34,
        "maxScore": 3,
        "epsilon": 0.5623
      },
      {
        "episode": 550,
        "avgScore": 0.22,
        "maxScore": 2,
        "epsilon": 0.5309
      },
      {
        "episode": 600,
        "avgScore": 0.74,
        "maxScore": 6,
        "epsilon": 0.5012
      },
      {
        "episode": 650,
        "avgScore": 0.48,
        "maxScore": 3,
        "epsilon": 0.4732
      },
      {
        "episode": 700,
        "avgScore": 0.64,
        "maxScore": 3,
        "epsilon": 0.4467
      },
      {
        "episode": 750,
        "avgScore": 0.76,
        "maxScore": 3,
        "epsilon": 0.4217
      },
      {
        "episode": 800,
        "avgScore": 0.54,
        "maxScore": 3,
        "epsilon": 0.3981
      },
      {
        "episode": 850,
        "avgScore": 0.94,
        "maxScore": 6,
        "epsilon": 0.3758
      },
      {
        "episode": 900,
        "avgScore": 0.52,
        "maxScore": 4,
        "epsilon": 0.3548
      },
      {
        "episode": 950,
        "avgScore": 1.04,
        "maxScore": 5,
        "epsilon": 0.335
      },
      {
        "episode": 1000,
        "avgScore": 0.7,
        "maxScore": 4,
        "epsilon": 0.3162
      },
      {
        "episode": 1050,
        "avgScore": 1.02,
        "maxScore": 7,
        "epsilon": 0.2985
      },
      {
        "episode": 1100,
        "avgScore": 1.12,
        "maxScore": 7,
        "epsilon": 0.2818
      },
      {
        "episode": 1150,
        "avgScore": 1.18,
        "maxScore": 9,
        "epsilon": 0.2661
      },
      {
        "episode": 1200,
        "avgScore": 1.54,
        "maxScore": 10,
        "epsilon": 0.2512
      },
      {
        "episode": 1250,
        "avgScore": 1.58,
        "maxScore": 9,
        "epsilon": 0.2371
      },
      {
        "episode": 1300,
        "avgScore": 1.38,
        "maxScore": 8,
        "epsilon": 0.2239
      },
      {
        "episode": 1350,
        "avgScore": 1.18,
        "maxScore": 7,
        "epsilon": 0.2113
      },
      {
        "episode": 1400,
        "avgScore": 1.56,
        "maxScore": 8,
        "epsilon": 0.1995
      },
      {
        "episode": 1450,
        "avgScore": 2,
        "maxScore": 10,
        "epsilon": 0.1884
      },
      {
        "episode": 1500,
        "avgScore": 1.96,
        "maxScore": 11,
        "epsilon": 0.1778
      },
      {
        "episode": 1550,
        "avgScore": 2.08,
        "maxScore": 6,
        "epsilon": 0.1679
      },
      {
        "episode": 1600,
        "avgScore": 1.38,
        "maxScore": 8,
        "epsilon": 0.1585
      },
      {
        "episode": 1650,
        "avgScore": 2.16,
        "maxScore": 12,
        "epsilon": 0.1496
      },
      {
        "episode": 1700,
        "avgScore": 1.86,
        "maxScore": 11,
        "epsilon": 0.1413
      },
      {
        "episode": 1750,
        "avgScore": 2.48,
        "maxScore": 11,
        "epsilon": 0.1334
      },
      {
        "episode": 1800,
        "avgScore": 3.34,
        "maxScore": 16,
        "epsilon": 0.1259
      },
      {
        "episode": 1850,
        "avgScore": 2.6,
        "maxScore": 21,
        "epsilon": 0.1189
      },
      {
        "episode": 1900,
        "avgScore": 1.84,
        "maxScore": 8,
        "epsilon": 0.1122
      },
      {
        "episode": 1950,
        "avgScore": 2.9,
        "maxScore": 19,
        "epsilon": 0.1059
      },
      {
        "episode": 2000,
        "avgScore": 2.98,
        "maxScore": 14,
        "epsilon": 0.1
      },
      {
        "episode": 2050,
        "avgScore": 4.02,
        "maxScore": 13,
        "epsilon": 0.0944
      },
      {
        "episode": 2100,
        "avgScore": 3.54,
        "maxScore": 13,
        "epsilon": 0.0891
      },
      {
        "episode": 2150,
        "avgScore": 2.62,
        "maxScore": 10,
        "epsilon": 0.0841
      },
      {
        "episode": 2200,
        "avgScore": 3.58,
        "maxScore": 15,
        "epsilon": 0.0794
      },
      {
        "episode": 2250,
        "avgScore": 3,
        "maxScore": 11,
        "epsilon": 0.075
      },
      {
        "episode": 2300,
        "avgScore": 3.16,
        "maxScore": 18,
        "epsilon": 0.0708
      },
      {
        "episode": 2350,
        "avgScore": 3.24,
        "maxScore": 17,
        "epsilon": 0.0668
      },
      {
        "episode": 2400,
        "avgScore": 2.26,
        "maxScore": 16,
        "epsilon": 0.0631
      },
      {
        "episode": 2450,
        "avgScore": 2.28,
        "maxScore": 19,
        "epsilon": 0.0596
      },
      {
        "episode": 2500,
        "avgScore": 2.38,
        "maxScore": 15,
        "epsilon": 0.0562
      },
      {
        "episode": 2550,
        "avgScore": 4.38,
        "maxScore": 24,
        "epsilon": 0.0531
      },
      {
        "episode": 2600,
        "avgScore": 3.7,
        "maxScore": 25,
        "epsilon": 0.0501
      },
      {
        "episode": 2650,
        "avgScore": 3.66,
        "maxScore": 39,
        "epsilon": 0.0473
      },
      {
        "episode": 2700,
        "avgScore": 4.88,
        "maxScore": 22,
        "epsilon": 0.0447
      },
      {
        "episode": 2750,
        "avgScore": 3.66,
        "maxScore": 18,
        "epsilon": 0.0422
      },
      {
        "episode": 2800,
        "avgScore": 2.86,
        "maxScore": 18,
        "epsilon": 0.0398
      },
      {
        "episode": 2850,
        "avgScore": 3.72,
        "maxScore": 20,
        "epsilon": 0.0376
      },
      {
        "episode": 2900,
        "avgScore": 4.62,
        "maxScore": 29,
        "epsilon": 0.0355
      },
      {
        "episode": 2950,
        "avgScore": 4.48,
        "maxScore": 17,
        "epsilon": 0.0335
      },
      {
        "episode": 3000,
        "avgScore": 6.28,
        "maxScore": 31,
        "epsilon": 0.0316
      },
      {
        "episode": 3050,
        "avgScore": 7.38,
        "maxScore": 43,
        "epsilon": 0.0299
      },
      {
        "episode": 3100,
        "avgScore": 8.94,
        "maxScore": 48,
        "epsilon": 0.0282
      },
      {
        "episode": 3150,
        "avgScore": 8.96,
        "maxScore": 28,
        "epsilon": 0.0266
      },
      {
        "episode": 3200,
        "avgScore": 7.04,
        "maxScore": 26,
        "epsilon": 0.0251
      },
      {
        "episode": 3250,
        "avgScore": 8.12,
        "maxScore": 37,
        "epsilon": 0.0237
      },
      {
        "episode": 3300,
        "avgScore": 5.6,
        "maxScore": 26,
        "epsilon": 0.0224
      },
      {
        "episode": 3350,
        "avgScore": 7.74,
        "maxScore": 26,
        "epsilon": 0.0211
      },
      {
        "episode": 3400,
        "avgScore": 5.1,
        "maxScore": 20,
        "epsilon": 0.02
      },
      {
        "episode": 3450,
        "avgScore": 8.72,
        "maxScore": 35,
        "epsilon": 0.0188
      },
      {
        "episode": 3500,
        "avgScore": 9.16,
        "maxScore": 47,
        "epsilon": 0.0178
      },
      {
        "episode": 3550,
        "avgScore": 7.82,
        "maxScore": 31,
        "epsilon": 0.0168
      },
      {
        "episode": 3600,
        "avgScore": 9.74,
        "maxScore": 48,
        "epsilon": 0.0158
      },
      {
        "episode": 3650,
        "avgScore": 8.68,
        "maxScore": 43,
        "epsilon": 0.015
      },
      {
        "episode": 3700,
        "avgScore": 7.72,
        "maxScore": 48,
        "epsilon": 0.0141
      },
      {
        "episode": 3750,
        "avgScore": 7.32,
        "maxScore": 29,
        "epsilon": 0.0133
      },
      {
        "episode": 3800,
        "avgScore": 8.66,
        "maxScore": 34,
        "epsilon": 0.0126
      },
      {
        "episode": 3850,
        "avgScore": 4.48,
        "maxScore": 25,
        "epsilon": 0.0119
      },
      {
        "episode": 3900,
        "avgScore": 8.62,
        "maxScore": 33,
        "epsilon": 0.0112
      },
      {
        "episode": 3950,
        "avgScore": 7.48,
        "maxScore": 30,
        "epsilon": 0.0106
      },
      {
        "episode": 4000,
        "avgScore": 11.86,
        "maxScore": 44,
        "epsilon": 0.01
      },
      {
        "episode": 4050,
        "avgScore": 13.34,
        "maxScore": 48,
        "epsilon": 0.01
      },
      {
        "episode": 4100,
        "avgScore": 4.04,
        "maxScore": 20,
        "epsilon": 0.01
      },
      {
        "episode": 4150,
        "avgScore": 2.9,
        "maxScore": 12,
        "epsilon": 0.01
      },
      {
        "episode": 4200,
        "avgScore": 1.66,
        "maxScore": 18,
        "epsilon": 0.01
      },
      {
        "episode": 4250,
        "avgScore": 3.48,
        "maxScore": 32,
        "epsilon": 0.01
      },
      {
        "episode": 4300,
        "avgScore": 5.22,
        "maxScore": 35,
        "epsilon": 0.01
      },
      {
        "episode": 4350,
        "avgScore": 7.36,
        "maxScore": 33,
        "epsilon": 0.01
      },
      {
        "episode": 4400,
        "avgScore": 4.92,
        "maxScore": 15,
        "epsilon": 0.01
      },
      {
        "episode": 4450,
        "avgScore": 4.94,
        "maxScore": 15,
        "epsilon": 0.01
      },
      {
        "episode": 4500,
        "avgScore": 6.08,
        "maxScore": 18,
        "epsilon": 0.01
      },
      {
        "episode": 4550,
        "avgScore": 7.08,
        "maxScore": 35,
        "epsilon": 0.01
      },
      {
        "episode": 4600,
        "avgScore": 6.18,
        "maxScore": 48,
        "epsilon": 0.01
      },
      {
        "episode": 4650,
        "avgScore": 5.98,
        "maxScore": 24,
        "epsilon": 0.01
      },
      {
        "episode": 4700,
        "avgScore": 3.84,
        "maxScore": 40,
        "epsilon": 0.01
      },
      {
        "episode": 4750,
        "avgScore": 6.2,
        "maxScore": 31,
        "epsilon": 0.01
      },
      {
        "episode": 4800,
        "avgScore": 7.7,
        "maxScore": 41,
        "epsilon": 0.01
      },
      {
        "episode": 4850,
        "avgScore": 8.14,
        "maxScore": 44,
        "epsilon": 0.01
      },
      {
        "episode": 4900,
        "avgScore": 6.9,
        "maxScore": 27,
        "epsilon": 0.01
      },
      {
        "episode": 4950,
        "avgScore": 8.46,
        "maxScore": 37,
        "epsilon": 0.01
      },
      {
        "episode": 5000,
        "avgScore": 6.72,
        "maxScore": 31,
        "epsilon": 0.01
      }
    ],
    "checkpoints": [
      {
        "episode": 500,
        "mean": 2.73,
        "max": 11,
        "min": 0,
        "stdDev": 2.41,
        "median": 2
      },
      {
        "episode": 1000,
        "mean": 7.43,
        "max": 33,
        "min": 0,
        "stdDev": 7.05,
        "median": 5.5
      },
      {
        "episode": 1500,
        "mean": 9.62,
        "max": 32,
        "min": 0,
        "stdDev": 8.36,
        "median": 8
      },
      {
        "episode": 2000,
        "mean": 12.15,
        "max": 48,
        "min": 0,
        "stdDev": 9.59,
        "median": 9
      },
      {
        "episode": 2500,
        "mean": 7.17,
        "max": 40,
        "min": 0,
        "stdDev": 8.67,
        "median": 4
      },
      {
        "episode": 3000,
        "mean": 11.58,
        "max": 36,
        "min": 0,
        "stdDev": 7.95,
        "median": 10
      },
      {
        "episode": 3500,
        "mean": 9.28,
        "max": 42,
        "min": 1,
        "stdDev": 8.61,
        "median": 7
      },
      {
        "episode": 4000,
        "mean": 11.5,
        "max": 48,
        "min": 0,
        "stdDev": 10.84,
        "median": 7.5
      },
      {
        "episode": 4500,
        "mean": 8.75,
        "max": 48,
        "min": 0,
        "stdDev": 8.79,
        "median": 6
      },
      {
        "episode": 5000,
        "mean": 7.72,
        "max": 41,
        "min": 1,
        "stdDev": 7.3,
        "median": 6
      }
    ],
    "finalEval": {
      "mean": 7.09,
      "max": 41,
      "min": 1,
      "stdDev": 6.47,
      "median": 5,
      "episodes": 200,
      "rawScores": [
        6,
        8,
        5,
        2,
        1,
        24,
        10,
        6,
        2,
        4,
        9,
        2,
        1,
        1,
        3,
        41,
        7,
        8,
        4,
        6,
        16,
        3,
        8,
        1,
        2,
        10,
        6,
        3,
        4,
        14,
        11,
        2,
        16,
        3,
        4,
        1,
        6,
        1,
        1,
        13,
        4,
        26,
        10,
        4,
        9,
        1,
        5,
        2,
        1,
        8,
        14,
        2,
        17,
        2,
        2,
        5,
        13,
        6,
        19,
        1,
        3,
        7,
        16,
        6,
        18,
        2,
        5,
        16,
        7,
        9,
        18,
        5,
        3,
        2,
        5,
        7,
        1,
        3,
        19,
        27,
        13,
        7,
        2,
        8,
        2,
        1,
        8,
        13,
        4,
        8,
        3,
        5,
        15,
        35,
        7,
        14,
        2,
        5,
        6,
        9,
        4,
        1,
        1,
        2,
        6,
        2,
        10,
        9,
        6,
        2,
        5,
        1,
        2,
        1,
        6,
        16,
        1,
        1,
        1,
        8,
        10,
        24,
        16,
        1,
        1,
        9,
        8,
        7,
        3,
        9,
        2,
        6,
        15,
        5,
        16,
        10,
        14,
        2,
        7,
        2,
        3,
        4,
        7,
        11,
        1,
        3,
        20,
        6,
        5,
        3,
        7,
        9,
        1,
        2,
        1,
        12,
        3,
        4,
        2,
        1,
        4,
        2,
        2,
        14,
        11,
        1,
        1,
        19,
        5,
        3,
        6,
        1,
        2,
        19,
        3,
        14,
        5,
        15,
        13,
        1,
        2,
        5,
        4,
        22,
        2,
        5,
        9,
        7,
        1,
        7,
        2,
        11,
        2,
        10,
        7,
        14,
        10,
        8,
        14,
        7
      ]
    }
  }
}